{
  "trialLabel": "Crossup Starter",
  "tutorialSetup": {
    "positions": [
      244320279784771,
      450359962737049
    ]
  },
  "setup": {
    "versusMode": "tutorial",
    "matchId": 1782363119003,
    "stageId": "train_day",
    "players": [
      {
        "playerIndex": 0,
        "characters": [
          {
            "charId": "sword",
            "colorIndex": 0,
            "assistIndex": 0
          }
        ]
      },
      {
        "playerIndex": 1,
        "characters": [
          {
            "charId": "sword",
            "colorIndex": 1,
            "assistIndex": 0
          }
        ]
      }
    ],
    "settings": {
      "clock": 300,
      "meter": 1
    }
  },
  "trial": {
    "duration": 421,
    "events": [
      [
        "sword",
        "H",
        "A",
        [
          205
        ],
        "OA_Normal_jB"
      ],
      [
        "sword",
        "H",
        "A",
        [
          203,
          207
        ],
        "Sword_Special_Air_Tatsu4"
      ],
      [
        "sword",
        "H",
        "G",
        [
          204
        ],
        "OA_Normal_5A"
      ],
      [
        "sword",
        "H",
        "G",
        [
          205
        ],
        "OA_Normal_5B"
      ],
      [
        "sword",
        "H",
        "G",
        [
          206
        ],
        "OA_Normal_5C"
      ],
      [
        "sword",
        "H",
        "G",
        [
          203,
          207
        ],
        "Sword_Special_RunningGrabDash"
      ],
      [
        "sword",
        "H",
        "G",
        [],
        "Sword_Special_RunningGrabToss"
      ],
      [
        "sword",
        "H",
        "G",
        [
          212
        ],
        "Super_FlurryRush"
      ],
      [
        "sword",
        "H",
        "G",
        [],
        "Super_FlurryRush_OnHit"
      ]
    ],
    "inputs": [
      [
        [
          29,
          60000000000000
        ],
        [
          30,
          20060000000000
        ],
        [
          31,
          20020000000000
        ],
        [
          32,
          20020000000000
        ],
        [
          33,
          20020000000000
        ],
        [
          34,
          30020000000000
        ],
        [
          35,
          20000000000
        ],
        [
          36,
          30000000000
        ],
        [
          61,
          600000000
        ],
        [
          62,
          200000000
        ],
        [
          63,
          200000000
        ],
        [
          64,
          200000000
        ],
        [
          65,
          200000000
        ],
        [
          66,
          200000000
        ],
        [
          67,
          200000000
        ],
        [
          68,
          200000000
        ],
        [
          69,
          300000000
        ],
        [
          70,
          200000000
        ],
        [
          72,
          600000000000
        ],
        [
          73,
          200000000000
        ],
        [
          74,
          200000000000
        ],
        [
          75,
          200000000000
        ],
        [
          76,
          200000000000
        ],
        [
          77,
          200006000000
        ],
        [
          78,
          200002000000
        ],
        [
          79,
          200002000000
        ],
        [
          80,
          200002000000
        ],
        [
          81,
          200002000000
        ],
        [
          82,
          200002000000
        ],
        [
          83,
          200002000000
        ],
        [
          84,
          200003000000
        ],
        [
          85,
          200000000000
        ],
        [
          86,
          300000000000
        ],
        [
          146,
          6000000000
        ],
        [
          147,
          2000000000
        ],
        [
          148,
          2000000000
        ],
        [
          149,
          2000000000
        ],
        [
          150,
          2000000000
        ],
        [
          151,
          2000000000
        ],
        [
          152,
          3000000000
        ],
        [
          155,
          600000000
        ],
        [
          156,
          200000000
        ],
        [
          157,
          200000000
        ],
        [
          158,
          200000000
        ],
        [
          159,
          200000000
        ],
        [
          160,
          200000000
        ],
        [
          161,
          200000000
        ],
        [
          162,
          300000000
        ],
        [
          176,
          60000000
        ],
        [
          177,
          20000000
        ],
        [
          178,
          20000000
        ],
        [
          179,
          20000000
        ],
        [
          180,
          20000000
        ],
        [
          181,
          20000000
        ],
        [
          182,
          20000000
        ],
        [
          183,
          20000000
        ],
        [
          184,
          20000000
        ],
        [
          185,
          30000000
        ],
        [
          197,
          60000000000
        ],
        [
          198,
          20000000000
        ],
        [
          199,
          20000000000
        ],
        [
          200,
          20006000000
        ],
        [
          201,
          20002000000
        ],
        [
          202,
          20002000000
        ],
        [
          203,
          30002000000
        ],
        [
          204,
          20002000000
        ],
        [
          205,
          3000000
        ],
        [
          206,
          2000000
        ],
        [
          289,
          60
        ],
        [
          290,
          20
        ],
        [
          291,
          20
        ],
        [
          292,
          20
        ],
        [
          293,
          20
        ],
        [
          294,
          20
        ],
        [
          295,
          30
        ]
      ],
      []
    ]
  }
}